imagezmq/__init__.py
imagezmq/__version__.py
imagezmq/imagezmq.py
imagezmq-1.2.0.dist-info/LICENSE.txt
imagezmq-1.2.0.dist-info/METADATA
imagezmq-1.2.0.dist-info/WHEEL
imagezmq-1.2.0.dist-info/top_level.txt
imagezmq-1.2.0.dist-info/RECORD
