Metadata-Version: 2.1
Name: imagezmq
Version: 1.2.0
Summary: Transporting OpenCV images via ZMQ
Home-page: https://github.com/jeffbass/imagezmq
Author: Jeff Bass
Author-email: jeff@yin-yang-ranch.com
License: MIT
Keywords: opencv-python,pyzmq,raspberrypi
Classifier: Development Status :: 5 - Production/Stable
Classifier: Intended Audience :: Developers
Classifier: Natural Language :: English
Classifier: License :: OSI Approved :: MIT License
Classifier: Programming Language :: Python
Classifier: Programming Language :: Python :: 3
Classifier: Programming Language :: Python :: 3.5
Classifier: Programming Language :: Python :: 3.6
Classifier: Programming Language :: Python :: 3.7
Classifier: Programming Language :: Python :: 3.8
Classifier: Programming Language :: Python :: 3.9
Classifier: Programming Language :: Python :: 3.10
Classifier: Programming Language :: Python :: 3.11
Classifier: Programming Language :: Python :: Implementation :: CPython
Classifier: Topic :: Software Development :: Libraries
Requires-Python: >=3.5
License-File: LICENSE.txt
Requires-Dist: pyzmq >=16.0
Requires-Dist: numpy >=1.13
